{
  "top": [],
  "side": [
    {
      "title": "Рабочий стол",
      "href": "dashboard",
      "children": [],
      "icon": "garage"
    },
    {
      "title": "Заказы",
      "href": "orders",
      "children": [],
      "icon": "delivery"
    },
    {
      "title": "Сотрудники",
      "href": "users",
      "children": [],
      "icon": "customers"
    },
    {
      "title": "Должности",
      "href": "roles",
      "children": [],
      "icon": "id-card"
    },
    {
      "title": "Платежи",
      "href": "payments",
      "children": [],
      "icon": "tag",
      "required_permissions": [
        "payments_get"
      ]
    },
    {
      "title": "Списки",
      "href": "lists",
      "children": [
        {
          "title": "Компании",
          "href": "companies"
        },
        {
          "title": "Контакты",
          "href": "contacts"
        },
        {
          "title": "Перевозимые авто",
          "href": "vehicles"
        }
      ],
      "icon": "bullet-list"
    },
    {
      "title": "Парк авто",
      "href": "",
      "children": [
        {
          "title": "Водители",
          "href": "drivers"
        },
        {
          "title": "Автомобили",
          "href": "cars"
        },
        {
          "title": "Прицепы",
          "href": "trailers"
        }
      ],
      "icon": "shipping-van"
    },
    {
      "title": "Документы",
      "href": "documents",
      "children": [],
      "icon": "reading"
    },
    {
      "title": "Продажи",
      "href": "sales",
      "children": [],
      "icon": "e-commerce"
    },
    {
      "title": "Расходы",
      "href": "expenses",
      "children": [],
      "icon": "reading"
    },
    {
      "title": "Утилиты",
      "href": "ads",
      "children": [],
      "icon": "conversation"
    },
    {
      "title": "Онлайн чат",
      "href": "chat",
      "children": [],
      "icon": "reading"
    },
    {
      "title": "Аналитика",
      "href": "reports",
      "children": [
        {
          "title": "Отчет диспетчера",
          "href": "dispatcherReport"
        },
        {
          "title": "Отчет Driver",
          "href": "driverReport"
        },
        {
          "title": "Отчет Owner Operator",
          "href": "ownerReport"
        },
        {
          "title": "Отчет администратора",
          "href": "adminReport"
        },
        {
          "title": "Отчет руководителя",
          "href": "directorReport"
        },
        {
          "title": "Отчет бухгалтера",
          "href": "accountantReport"
        },
        {
          "title": "Отчет инвестора",
          "href": "investorReport"
        },
        {
          "title": "Отчет брокера",
          "href": "brokerReport"
        },
        {
          "title": "Отчет технического специалиста",
          "href": "technicalReport"
        },
        {
          "title": "Расходы",
          "href": "expenses"
        },
        {
          "title": "Задачи",
          "href": "tasks"
        }
      ],
      "icon": "performance"
    },
    {
      "title": "Настройки",
      "href": "settings",
      "children": [
        {
          "title": "Список позиций",
          "href": "positions"
        },
        {
          "title": "Доска объявлений",
          "href": "notice_board"
        },
        {
          "title": "Напоминания",
          "href": "reminders"
        },
        {
          "title": "Типы штрафов для диспетчеров",
          "href": "finesDispatchers"
        },
        {
          "title": "Типы штрафов для водителей",
          "href": "finesDrivers"
        },
        {
          "title": "Типы бонусов для диспетчеров",
          "href": "bonusDispatchers"
        },
        {
          "title": "Типы бонусов для водителей",
          "href": "bonusDrivers"
        },
        {
          "title": "Плановые ТО",
          "href": "maintenanceSchedules"
        },
        {
          "title": "Статусы оплаты",
          "href": "orderPayStatuses"
        },
        {
          "title": "Статусы заказов",
          "href": "orderStatuses"
        },
        {
          "title": "Источники заявок",
          "href": "orderSources"
        },
        {
          "title": "Категории документов",
          "href": "documentCategories"
        },
        {
          "title": "Категории компаний",
          "href": "companyCategories"
        },
        {
          "title": "Категории расходов",
          "href": "expenseCategories"
        },
        {
          "title": "Способы оплаты",
          "href": "paymentTypes"
        },
        {
          "title": "Роли",
          "href": "roles"
        },
        {
          "title": "Причины отмены заявок",
          "href": "reasons"
        },
        {
          "title": "Общие",
          "href": "settings"
        }
      ],
      "icon": "gear"
    }
  ]
}
