{"title":"История оплат","properties":[{"title":"ID заказа","article":"order_id","type":"int","default":null,"is_required":"Y"},{"title":"Общая стоимость","article":"cost","type":"float","default":null,"is_required":"Y"},{"title":"Оплачено","article":"paidFor","type":"float","default":null,"is_required":"Y"},{"title":"Осталось оплатить","article":"needPay","type":"float","default":null,"is_required":"Y"},{"title":"Способ оплаты","article":"paymentType_id","type":"int","default":null,"is_required":"N"}]}